jsonutil
