Metadata-Version: 1.0
Name: jsonutil
Version: 1.0.2
Summary: a wrapper around simplejson which deserializes decimals to Decimal instead of to float
Home-page: http://tahoe-lafs.org/trac/jsonutil
Author: Zooko O'Whielacronx
Author-email: zooko@simplegeo.com
License: Transitive Grace Period Public Licence
Platform: UNKNOWN
Classifier: Development Status :: 5 - Production/Stable
Classifier: License :: OSI Approved :: GNU General Public License (GPL)
Classifier: License :: DFSG approved
Classifier: Intended Audience :: Developers
Classifier: Operating System :: OS Independent
Classifier: Natural Language :: English
Classifier: Programming Language :: Python
Classifier: Programming Language :: Python :: 2
Classifier: Programming Language :: Python :: 2.4
Classifier: Programming Language :: Python :: 2.5
Classifier: Programming Language :: Python :: 2.6
Classifier: Topic :: Utilities
Classifier: Topic :: Software Development :: Libraries
